apectoolpy/__init__.py
apectoolpy/main.py
apectoolpy/starter.py
apectoolpy/static_seismic.py
apectoolpy/wall-loads.py
apectoolpy-0.3.dist-info/METADATA
apectoolpy-0.3.dist-info/WHEEL
apectoolpy-0.3.dist-info/top_level.txt
apectoolpy-0.3.dist-info/RECORD
