Metadata-Version: 2.2
Name: apectoolpy
Version: 0.3
Summary: This APEC internal use only
Home-page: https://github.com/albertp16/apec-py
Author: Albert Pamonag
Author-email: albert@apeconsultancy.net
Classifier: Programming Language :: Python :: 3
Classifier: Operating System :: OS Independent
Dynamic: author
Dynamic: author-email
Dynamic: classifier
Dynamic: home-page
Dynamic: summary
